langtest/__init__.py
langtest/__main__.py
langtest/augmentation/__init__.py
langtest/augmentation/augmenter.py
langtest/augmentation/base.py
langtest/augmentation/debias.py
langtest/augmentation/utils.py
langtest/callback.py
langtest/config.py
langtest/data/ACIBench/aci_bench_test_1.json
langtest/data/ASDiv/test-tiny.jsonl
langtest/data/ASDiv/test.jsonl
langtest/data/BBQ/test-tiny.jsonl
langtest/data/BBQ/test.jsonl
langtest/data/BSS/test.jsonl
langtest/data/Bigbench/Abstract-narrative-understanding/test-tiny.jsonl
langtest/data/Bigbench/Abstract-narrative-understanding/test.jsonl
langtest/data/Bigbench/Causal-judgment/test-tiny.jsonl
langtest/data/Bigbench/Causal-judgment/test.jsonl
langtest/data/Bigbench/DisambiguationQA/test-tiny.jsonl
langtest/data/Bigbench/DisambiguationQA/test.jsonl
langtest/data/Bigbench/DisflQA/test-tiny.jsonl
langtest/data/Bigbench/DisflQA/test.jsonl
langtest/data/BoolQ/bias.jsonl
langtest/data/BoolQ/combined.jsonl
langtest/data/BoolQ/dev-tiny.jsonl
langtest/data/BoolQ/dev.jsonl
langtest/data/BoolQ/test-tiny.jsonl
langtest/data/BoolQ/test.jsonl
langtest/data/Clinical/Gastroenterology-files.jsonl
langtest/data/Clinical/Medical-files.jsonl
langtest/data/Clinical/Oromaxillofacial-files.jsonl
langtest/data/CommonsenseQA/test-tiny.jsonl
langtest/data/CommonsenseQA/test.jsonl
langtest/data/CommonsenseQA/validation-tiny.jsonl
langtest/data/CommonsenseQA/validation.jsonl
langtest/data/Consumer-Contracts/test.jsonl
langtest/data/Contracts/test.jsonl
langtest/data/Crows-Pairs/test.csv
langtest/data/DrugSwap/qa_generic_to_brand_v2.jsonl
langtest/data/Factual-Summary-Pairs/test.jsonl
langtest/data/Fiqa/test.jsonl
langtest/data/HellaSwag/test-tiny.jsonl
langtest/data/HellaSwag/test.jsonl
langtest/data/Legal-Support/test.jsonl
langtest/data/LiveQA/test.jsonl
langtest/data/LogiQA/test-tiny.jsonl
langtest/data/LogiQA/test.jsonl
langtest/data/MMLU/clinical.jsonl
langtest/data/MMLU/test-tiny.jsonl
langtest/data/MMLU/test.jsonl
langtest-2.7.0.dist-info/LICENSE
langtest-2.7.0.dist-info/METADATA
langtest-2.7.0.dist-info/WHEEL
langtest-2.7.0.dist-info/entry_points.txt
langtest-2.7.0.dist-info/RECORD
