Metadata-Version: 2.3
Name: langtest
Version: 2.7.0
Summary: Pacific AI provides a library for delivering safe & effective NLP models.
License: Apache-2.0
Keywords: LLM,NLP,AI,testing,robustness,bias,fairness,representation,accuracy,language processing,natural language understanding,machine learning,data science
Author: Pacific AI
Author-email: support@johnsnowlabs.com
Requires-Python: >=3.9,<4.0
Classifier: Development Status :: 5 - Production/Stable
Classifier: Intended Audience :: Developers
Classifier: License :: OSI Approved :: Apache Software License
Classifier: Programming Language :: Python :: 3
Classifier: Programming Language :: Python :: 3.9
Classifier: Programming Language :: Python :: 3.10
Classifier: Programming Language :: Python :: 3.11
Classifier: Programming Language :: Python :: 3.12
Classifier: Programming Language :: Python :: 3.13
Classifier: Programming Language :: Python :: 3.7
Classifier: Programming Language :: Python :: 3.8
Classifier: Topic :: Software Development :: Build Tools
Provides-Extra: ai21
Provides-Extra: cohere
Provides-Extra: databricks
Provides-Extra: datasets
Provides-Extra: evaluate
Provides-Extra: huggingface-hub
Provides-Extra: johnsnowlabs
Provides-Extra: llms
Provides-Extra: matplotlib
Provides-Extra: metaflow
Provides-Extra: mlflow
Provides-Extra: ollama-sdk
Provides-Extra: openai
Provides-Extra: spacy
Provides-Extra: transformers
Requires-Dist: accelerate (>=1.10.0,<2.0.0) ; extra == "transformers"
Requires-Dist: ai21 (>=1.1.0,<2.0.0) ; extra == "ai21"
Requires-Dist: click (>=8.1.7)
Requires-Dist: cohere (>=4.10.0,<5.0.0) ; extra == "cohere"
Requires-Dist: databricks-langchain (==0.5.1) ; (python_version >= "3.10" and python_version < "4.0") and (extra == "databricks")
Requires-Dist: datasets (>=3.6.0) ; extra == "transformers" or extra == "datasets"
Requires-Dist: deprecated (>=1.2.18,<2.0.0)
Requires-Dist: evaluate (>=0.4.0,<0.5.0) ; extra == "evaluate"
Requires-Dist: huggingface_hub (>0.16.0) ; extra == "huggingface-hub"
Requires-Dist: importlib-resources (>=5.10)
Requires-Dist: johnsnowlabs (>=6.0.4,<7.0.0) ; extra == "johnsnowlabs"
Requires-Dist: jsonlines (>=3.1.0)
Requires-Dist: langchain (>=0.3.15,<0.4.0) ; extra == "openai" or extra == "cohere" or extra == "ai21" or extra == "huggingface-hub" or extra == "databricks" or extra == "llms" or extra == "ollama-sdk"
Requires-Dist: langchain-community (==0.3.9) ; extra == "openai" or extra == "cohere" or extra == "ai21" or extra == "databricks" or extra == "llms" or extra == "ollama-sdk"
Requires-Dist: langchain-ollama (>=0.2.2,<0.3.0) ; extra == "llms"
Requires-Dist: langchain-openai (>=0.3.7,<0.4.0) ; extra == "openai" or extra == "databricks" or extra == "llms"
Requires-Dist: matplotlib (>=3.7.2,<4.0.0) ; extra == "matplotlib"
Requires-Dist: metaflow (>=2.9.0) ; extra == "metaflow"
Requires-Dist: mlflow (==3.1.1) ; extra == "mlflow"
Requires-Dist: nest-asyncio (>=1.5.0,<2.0.0)
Requires-Dist: ollama (>=0.4.7,<0.5.0) ; extra == "ollama-sdk"
Requires-Dist: openai (>=1.61.1,<2.0.0) ; extra == "openai"
Requires-Dist: openpyxl (>=3.1.5)
Requires-Dist: pandas (>=2.0.3,<3.0.0)
Requires-Dist: pillow (>=11.0.0)
Requires-Dist: pydantic (>=2.10.0)
Requires-Dist: pyyaml (>=6.0,<7.0)
Requires-Dist: rouge-score (>=0.1.2,<0.2.0) ; extra == "evaluate"
Requires-Dist: seqeval (>=1.2.0,<2.0.0) ; extra == "evaluate"
Requires-Dist: spacy (>=3.0.0) ; extra == "spacy"
Requires-Dist: tables (>=3.8.0)
Requires-Dist: torch (>=2.8.0,<3.0.0) ; extra == "transformers"
Requires-Dist: tqdm (>=4.67.1,<5.0.0)
Requires-Dist: transformers (>=4.52.4,<5.0.0) ; extra == "transformers"
Requires-Dist: typing-extensions (>=4.10.0,<5.0.0)
Project-URL: Documentation, https://langtest.org/docs/pages/docs/install
Project-URL: Homepage, https://www.langtest.org
Project-URL: Repository, https://github.com/Pacific-AI-Corp/langtest/
